{
  "project_info": {
    "project_number": "403757706301",
    "project_id": "chat-app-57d62",
    "storage_bucket": "chat-app-57d62.firebasestorage.app"
  },
  "client": [
    {
      "client_info": {
        "mobilesdk_app_id": "1:403757706301:android:85d336593dbb561bf44e54",
        "android_client_info": {
          "package_name": "com.example.chat_app"
        }
      },
      "oauth_client": [],
      "api_key": [
        {
          "current_key": "AIzaSyAYYy8zgEg_boIc5DRKhoejjUCMsA3fKjs"
        }
      ],
      "services": {
        "appinvite_service": {
          "other_platform_oauth_client": []
        }
      }
    },
    {
      "client_info": {
        "mobilesdk_app_id": "1:403757706301:android:e8d6f4708ef7e076f44e54",
        "android_client_info": {
          "package_name": "com.example.scholar_chat"
        }
      },
      "oauth_client": [],
      "api_key": [
        {
          "current_key": "AIzaSyAYYy8zgEg_boIc5DRKhoejjUCMsA3fKjs"
        }
      ],
      "services": {
        "appinvite_service": {
          "other_platform_oauth_client": []
        }
      }
    }
  ],
  "configuration_version": "1"
}